{
  "posts": [
    {
      "id": 5,
      "title": "Poderoso Deus",
      "body": "Faz morada em meu lar."
    },
    {
      "title": "Obrigado Senhor!",
      "body": "Rei dos Reis",
      "id": 6
    },
    {
      "id": 7,
      "title": "Bom dia com Deus",
      "body": "Obrigado Senhor"
    },
    {
      "id": 8,
      "title": "Estudar",
      "body": "Bíblia"
    },
    {
      "title": "Nest JS",
      "body": "Framework backend",
      "id": 9
    },
    {
      "id": 10,
      "title": "Deus no comando",
      "body": "Sempre!!!!!"
    }
  ]
}